globus_identity_mapping/__init__.py
globus_identity_mapping/errors.py
globus_identity_mapping/loader.py
globus_identity_mapping/mappers/__init__.py
globus_identity_mapping/mappers/abstract.py
globus_identity_mapping/mappers/expression.py
globus_identity_mapping/mappers/external_program.py
globus_identity_mapping/protocol/__init__.py
globus_identity_mapping/py.typed
globus_identity_mapping/schema/__init__.py
globus_identity_mapping/schema/data_type.py
globus_identity_mapping/schema/identity_mapping.py
globus_identity_mapping/schema/schema_version_checker.py
globus_identity_mapping/validating_mapper.py
globus_identity_mapping-0.5.0.dist-info/LICENSE
globus_identity_mapping-0.5.0.dist-info/METADATA
globus_identity_mapping-0.5.0.dist-info/WHEEL
globus_identity_mapping-0.5.0.dist-info/entry_points.txt
globus_identity_mapping-0.5.0.dist-info/RECORD
