Metadata-Version: 2.3
Name: globus-identity-mapping
Version: 0.5.0
Summary: 
Author: Kevin Hunter Kesling
Author-email: kevin@globus.org
Requires-Python: >=3.9
Classifier: Programming Language :: Python :: 3
Classifier: Programming Language :: Python :: 3.9
Classifier: Programming Language :: Python :: 3.10
Classifier: Programming Language :: Python :: 3.11
Classifier: Programming Language :: Python :: 3.12
Classifier: Programming Language :: Python :: 3.13
Provides-Extra: test
Requires-Dist: click (>=8.1.7,<9.0.0)
Requires-Dist: marshmallow (>=3.26.2,<4.0.0)
Requires-Dist: marshmallow-oneofschema (>=3.0.1,<4.0.0,!=3.1.0)
Requires-Dist: pytest (>=8.2,<8.3) ; extra == "test"
Requires-Dist: pytest-cov (>=5.0,<5.1) ; extra == "test"
Requires-Dist: pytest-mock (>=3.14,<3.15) ; extra == "test"
Requires-Dist: typing-extensions (>=4.11)
